AUTHORS.txt
CHANGES.txt
LICENSE.txt
MANIFEST.in
README.rst
setup.py
django_redactoreditor.egg-info/PKG-INFO
django_redactoreditor.egg-info/SOURCES.txt
django_redactoreditor.egg-info/dependency_links.txt
django_redactoreditor.egg-info/not-zip-safe
django_redactoreditor.egg-info/requires.txt
django_redactoreditor.egg-info/top_level.txt
redactor/__init__.py
redactor/fields.py
redactor/models.py
redactor/tests.py
redactor/utils.py
redactor/widgets.py
redactor/static/.DS_Store
redactor/static/django-redactor/lib/jquery-1.10.1.min.js
redactor/static/django-redactor/lib/jquery-1.9.0.min.js
redactor/static/django-redactor/redactor/admin_setup.js
redactor/static/django-redactor/redactor/redactor.js
redactor/static/django-redactor/redactor/redactor.min.js
redactor/static/django-redactor/redactor/setup.js
redactor/static/django-redactor/redactor/css/django_admin.css
redactor/static/django-redactor/redactor/css/docstyle.css
redactor/static/django-redactor/redactor/css/redactor.css
redactor/static/django-redactor/redactor/css/style.css
redactor/static/django-redactor/redactor/css/wym.css
redactor/static/django-redactor/redactor/langs/ar.js
redactor/static/django-redactor/redactor/langs/az.js
redactor/static/django-redactor/redactor/langs/ba.js
redactor/static/django-redactor/redactor/langs/bg.js
redactor/static/django-redactor/redactor/langs/by.js
redactor/static/django-redactor/redactor/langs/ca.js
redactor/static/django-redactor/redactor/langs/cs.js
redactor/static/django-redactor/redactor/langs/da.js
redactor/static/django-redactor/redactor/langs/de.js
redactor/static/django-redactor/redactor/langs/el.js
redactor/static/django-redactor/redactor/langs/en.js
redactor/static/django-redactor/redactor/langs/eo.js
redactor/static/django-redactor/redactor/langs/es.js
redactor/static/django-redactor/redactor/langs/es_ar.js
redactor/static/django-redactor/redactor/langs/fa.js
redactor/static/django-redactor/redactor/langs/fi.js
redactor/static/django-redactor/redactor/langs/fr.js
redactor/static/django-redactor/redactor/langs/ge.js
redactor/static/django-redactor/redactor/langs/he.js
redactor/static/django-redactor/redactor/langs/hr.js
redactor/static/django-redactor/redactor/langs/hu.js
redactor/static/django-redactor/redactor/langs/id.js
