Metadata-Version: 1.1
Name: django-redactoreditor
Version: 1.2.10
Summary: Integrates the Redactor Javascript WYSIWYG editor with Django.
Home-page: https://github.com/mazelife/django-redactoreditor
Author: James Stevenson
Author-email: james.m.stevenson at gmail dot com
License: CC licence, see LICENSE.txt
Platform: UNKNOWN
Classifier: Development Status :: 5 - Production/Stable
Classifier: Intended Audience :: Developers
Classifier: License :: Other/Proprietary License
Classifier: Programming Language :: Python
Classifier: Operating System :: OS Independent
Classifier: Topic :: Software Development :: Libraries
Classifier: Topic :: Utilities
Classifier: Environment :: Web Environment
Classifier: Framework :: Django
